medprompt/__init__.py
medprompt/bootstrap.py
medprompt/helpers.py
medprompt/med_prompt.py
medprompt/agents/__init__.py
medprompt/agents/base_medprompt_agent.py
medprompt/agents/fhir_agent.py
medprompt/chains/__init__.py
medprompt/chains/base_medprompt_chain.py
medprompt/chains/clinical_summary_chain.py
medprompt/chains/fhir_query_chain.py
medprompt/chains/rag_chain.py
medprompt/chains/self_gen_cot_chain.py
medprompt/hosting/Dockerfile
medprompt/hosting/__init__.py
medprompt/hosting/app.py
medprompt/hosting/base_model.py
medprompt/hosting/base_server.py
medprompt/hosting/requirements.txt
medprompt/llms/__init__.py
medprompt/llms/base_medprompt_llm.py
medprompt/space/__init__.py
medprompt/space/fhir_agent.py
medprompt/templates/base_medprompt_agent_prefix_v1.jinja
medprompt/templates/base_medprompt_agent_suffix_v1.jinja
medprompt/templates/condition_v1.jinja
medprompt/templates/default.jinja
medprompt/templates/diagnosticreport_v1.jinja
medprompt/templates/documentreference_v1.jinja
medprompt/templates/fhir_agent_prefix_v1.jinja
medprompt/templates/fhir_agent_suffix_v1.jinja
medprompt/templates/fhir_rails_v1.xml
medprompt/templates/fhir_search_oai_chat_v1.json
medprompt/templates/medicationrequest_v1.jinja
medprompt/templates/observation_v1.jinja
medprompt/templates/patient_v1.jinja
medprompt/templates/procedure_v1.jinja
medprompt/templates/rag_chain_v1.jinja
medprompt/templates/summary_v1.jinja
medprompt/tools/__init__.py
medprompt/tools/create_embedding.py
medprompt/tools/expand_concepts.py
medprompt/tools/fhir_to_text.py
medprompt/tools/find_patient.py
medprompt/utils/__init__.py
medprompt/utils/fhir_server.py
medprompt/utils/get_medical_record.py
medprompt/utils/hapi_server.py
medprompt-0.16.0.dist-info/METADATA
medprompt-0.16.0.dist-info/WHEEL
medprompt-0.16.0.dist-info/top_level.txt
medprompt-0.16.0.dist-info/RECORD
