Metadata-Version: 2.1
Name: medprompt
Version: 0.16.0
Summary: Healthcare inspared LLM prompts
Home-page: https://nuchange.ca
Author: Bell Eapen
Author-email: github_public@gulfdoctor.net
License: Apache-2.0
Project-URL: Documentation, https://pyscaffold.org/
Platform: any
Classifier: Development Status :: 4 - Beta
Classifier: Programming Language :: Python
Requires-Dist: Jinja2
Requires-Dist: langchain (==0.0.350)
Requires-Dist: httpx
Requires-Dist: python-dotenv
Requires-Dist: PyPDF[crypto]
Requires-Dist: striprtf (==0.0.26)
Requires-Dist: kink (==0.7.0)
Requires-Dist: guardrails-ai
Requires-Dist: huggingface-hub
Requires-Dist: gensim
Requires-Dist: agency
Requires-Dist: overrides
Requires-Dist: langchain-community (==0.0.6)
Requires-Dist: langchain-core (==0.1.3)
Requires-Dist: importlib-metadata ; python_version < "3.8"
Provides-Extra: embedding
Requires-Dist: sentence-transformers ; extra == 'embedding'
Requires-Dist: faiss-cpu ; extra == 'embedding'
Requires-Dist: chromadb (==0.3.29) ; extra == 'embedding'
Requires-Dist: redis ; extra == 'embedding'
Requires-Dist: gpt4all ; extra == 'embedding'
Provides-Extra: testing
Requires-Dist: setuptools ; extra == 'testing'
Requires-Dist: pytest ; extra == 'testing'
Requires-Dist: pytest-cov ; extra == 'testing'
